fewlearn/__init__.py
fewlearn/backbones/__init__.py
fewlearn/backbones/registry.py
fewlearn/core/__init__.py
fewlearn/core/minds.py
fewlearn/core/protocols.py
fewlearn/evaluation/__init__.py
fewlearn/evaluation/evaluator.py
fewlearn/evaluation/metrics.py
fewlearn/models/__init__.py
fewlearn/models/base.py
fewlearn/models/prototypical.py
fewlearn/tests/__init__.py
fewlearn/tests/test_minds.py
fewlearn/tests/test_prototypical.py
fewlearn/utils/__init__.py
fewlearn/utils/data_utils.py
fewlearn/utils/export.py
fewlearn/utils/samplers.py
fewlearn/visualization/__init__.py
fewlearn/visualization/plotting.py
fewlearn-0.1.2.dist-info/METADATA
fewlearn-0.1.2.dist-info/WHEEL
fewlearn-0.1.2.dist-info/top_level.txt
fewlearn-0.1.2.dist-info/RECORD
