Metadata-Version: 2.4
Name: fewlearn
Version: 0.1.2
Summary: A Python module for few-shot learning with pretrained models
Home-page: https://github.com/AdityaSharma2485/fewlearn
Author: Aditya Sharma
Author-email: adityasharma.2485@gmail.com
License: MIT License
Project-URL: Homepage, https://github.com/AdityaSharma2485/fewlearn
Project-URL: Bug Tracker, https://github.com/AdityaSharma2485/fewlearn/issues
Classifier: Programming Language :: Python :: 3
Classifier: License :: OSI Approved :: MIT License
Classifier: Operating System :: OS Independent
Classifier: Topic :: Scientific/Engineering :: Artificial Intelligence
Classifier: Development Status :: 4 - Beta
Requires-Python: >=3.7
Dynamic: author
Dynamic: author-email
Dynamic: home-page
Dynamic: requires-python
